[
    {
        "imageSrc": "/images/metalica_gg.jpeg",
        "valor": 109.90,
        "titulo": " CAMISA BANDA METALICA BLACK ALBUM ",
        "carga_horaria": "2h",
        "id": 1,
        "descricao": "Descrição Camisa Black Album GG"
    },
    {
        "imageSrc": "/images/copo.jpg",
        "valor": 119.90,
        "titulo": "COPO CACILDIS",
        "carga_horaria": "12h",
        "id": 2,
        "descricao": " Disponível na Hobby Store Copo Cacildis - Ruvolo -  Disponível nos 3 modelos R$44,90 Valor sujeito à alterações. Aceitamos Cartões e PIX "
    },
    {
        "imageSrc": "https://imgur.com/n7KEBqF.png",
        "valor": 129.90,
        "titulo": "Atendimento Pr\u00e9 Hospitalar (Primeiros Socorros) B\u00e1sico",
        "carga_horaria": "9h",
        "id": 3,
        "descricao": "Capacitar o aluno na realiza\u00e7\u00e3o de a\u00e7\u00f5es emergenciais em caso de acidentes industriais ou dom\u00e9sticos. Embora o conte\u00fado do curso esteja aberto a todos os interessados em ingressar nesta \u00e1rea, alunos com experi\u00eancia anterior em \u00e1reas afins ter\u00e3o melhor aproveitamento devido \u00e0 sua realidade profissional."
    }
]